ninja_bear_distributor_git/__init__.py
ninja_bear_distributor_git/distributor.py
ninja_bear_distributor_git-0.1.1.dist-info/LICENSE
ninja_bear_distributor_git-0.1.1.dist-info/METADATA
ninja_bear_distributor_git-0.1.1.dist-info/WHEEL
ninja_bear_distributor_git-0.1.1.dist-info/entry_points.txt
ninja_bear_distributor_git-0.1.1.dist-info/top_level.txt
ninja_bear_distributor_git-0.1.1.dist-info/RECORD
