Metadata-Version: 2.1
Name: ninja-bear-distributor-git
Version: 0.1.1
Summary: Git distributor support for ninja-bear
Home-page: https://github.com/monstermichl/ninja-bear-distributor-git.git
Author: monstermichl
Keywords: ninja-bear,plugin,distributor,git
Classifier: Programming Language :: Python :: 3
Classifier: Operating System :: OS Independent
Requires-Python: >=3.10
License-File: LICENSE
Provides-Extra: dev
Requires-Dist: ninja-bear>=0.1.4; extra == "dev"
Requires-Dist: wheel>=0.41.1; extra == "dev"
Requires-Dist: twine>=4.0.2; extra == "dev"
Requires-Dist: ruff>=0.0.47; extra == "dev"
Requires-Dist: coverage>=7.2.7; extra == "dev"
